zhmc_prometheus_exporter/__init__.py
zhmc_prometheus_exporter/_exceptions.py
zhmc_prometheus_exporter/_logging.py
zhmc_prometheus_exporter/_resource_cache.py
zhmc_prometheus_exporter/_version.py
zhmc_prometheus_exporter/_version_scm.py
zhmc_prometheus_exporter/zhmc_prometheus_exporter.py
zhmc_prometheus_exporter/data/metrics.yaml
zhmc_prometheus_exporter/schemas/config_schema.yaml
zhmc_prometheus_exporter/schemas/metrics_schema.yaml
zhmc_prometheus_exporter/vendor/__init__.py
zhmc_prometheus_exporter/vendor/prometheus_client/__init__.py
zhmc_prometheus_exporter/vendor/prometheus_client/asgi.py
zhmc_prometheus_exporter/vendor/prometheus_client/context_managers.py
zhmc_prometheus_exporter/vendor/prometheus_client/core.py
zhmc_prometheus_exporter/vendor/prometheus_client/decorator.py
zhmc_prometheus_exporter/vendor/prometheus_client/exposition.py
zhmc_prometheus_exporter/vendor/prometheus_client/gc_collector.py
zhmc_prometheus_exporter/vendor/prometheus_client/metrics.py
zhmc_prometheus_exporter/vendor/prometheus_client/metrics_core.py
zhmc_prometheus_exporter/vendor/prometheus_client/mmap_dict.py
zhmc_prometheus_exporter/vendor/prometheus_client/multiprocess.py
zhmc_prometheus_exporter/vendor/prometheus_client/parser.py
zhmc_prometheus_exporter/vendor/prometheus_client/platform_collector.py
zhmc_prometheus_exporter/vendor/prometheus_client/process_collector.py
zhmc_prometheus_exporter/vendor/prometheus_client/py.typed
zhmc_prometheus_exporter/vendor/prometheus_client/registry.py
zhmc_prometheus_exporter/vendor/prometheus_client/samples.py
zhmc_prometheus_exporter/vendor/prometheus_client/utils.py
zhmc_prometheus_exporter/vendor/prometheus_client/values.py
zhmc_prometheus_exporter/vendor/prometheus_client/bridge/__init__.py
zhmc_prometheus_exporter/vendor/prometheus_client/bridge/graphite.py
zhmc_prometheus_exporter/vendor/prometheus_client/openmetrics/__init__.py
zhmc_prometheus_exporter/vendor/prometheus_client/openmetrics/exposition.py
zhmc_prometheus_exporter-2.3.1.dist-info/licenses/AUTHORS.md
zhmc_prometheus_exporter-2.3.1.dist-info/licenses/LICENSE
zhmc_prometheus_exporter-2.3.1.dist-info/METADATA
zhmc_prometheus_exporter-2.3.1.dist-info/WHEEL
zhmc_prometheus_exporter-2.3.1.dist-info/entry_points.txt
zhmc_prometheus_exporter-2.3.1.dist-info/top_level.txt
zhmc_prometheus_exporter-2.3.1.dist-info/zip-safe
zhmc_prometheus_exporter-2.3.1.dist-info/RECORD
