Metadata-Version: 2.4
Name: zhmc_prometheus_exporter
Version: 2.3.1
Summary: IBM Z HMC Prometheus Exporter
Author-email: Jakob Naucke <jakob.naucke@ibm.com>
Maintainer-email: Andreas Maier <maiera@de.ibm.com>, Kathir Velusamy <kathir.velu@in.ibm.com'>
License: Apache License, Version 2.0
Project-URL: Homepage, https://github.com/zhmcclient/zhmc-prometheus-exporter
Project-URL: Bug Tracker, https://github.com/zhmcclient/zhmc-prometheus-exporter/issues
Project-URL: Documentation, https://zhmc-prometheus-exporter.readthedocs.io/en/stable/
Project-URL: Source Code, https://github.com/zhmcclient/zhmc-prometheus-exporter
Project-URL: Changelog, https://zhmc-prometheus-exporter.readthedocs.io/en/stable/changes.html
Keywords: hmc,prometheus,monitoring
Platform: any
Classifier: License :: OSI Approved :: Apache Software License
Classifier: Development Status :: 5 - Production/Stable
Classifier: Intended Audience :: Information Technology
Classifier: Topic :: System :: Systems Administration
Classifier: Environment :: Console
Classifier: Operating System :: OS Independent
Classifier: Programming Language :: Python :: 3
Classifier: Programming Language :: Python :: 3.8
Classifier: Programming Language :: Python :: 3.9
Classifier: Programming Language :: Python :: 3.10
Classifier: Programming Language :: Python :: 3.11
Classifier: Programming Language :: Python :: 3.12
Classifier: Programming Language :: Python :: 3.13
Requires-Python: >=3.8
License-File: LICENSE
License-File: AUTHORS.md
Requires-Dist: zhmcclient>=1.24.0
Requires-Dist: urllib3>=2.2.3; python_version == "3.8"
Requires-Dist: urllib3>=2.5.0; python_version >= "3.9"
Requires-Dist: jsonschema>=4.18.0
Requires-Dist: Jinja2>=3.1.6
Requires-Dist: ruamel.yaml>=0.18.6
Requires-Dist: PyYAML>=6.0.2
Requires-Dist: pyrsistent>=0.20.0
Dynamic: license-file
